.codeclimate.yml
.landscape.yml
.travis.yml
AUTHORS
ChangeLog
LICENSE-2.0.txt
README.rst
conftest.py
requirements.txt
setup.cfg
setup.py
.circleci/config.yml
conda/dev-environment.yml
conda/meta.yaml
docs/Makefile
docs/conf.py
docs/index.rst
docs/readme.rst
test/.empty
test/file1
test/file2
test/otherfile
test/test_manifest.py
test/testfiles/simple_xy_0.nc
test/testfiles/simple_xy_1.nc
test/testfiles/simple_xy_2.nc
yamanifest/__init__.py
yamanifest/hashing.py
yamanifest/manifest.py
yamanifest/utils.py
yamanifest/yamf.py
yamanifest.egg-info/PKG-INFO
yamanifest.egg-info/SOURCES.txt
yamanifest.egg-info/dependency_links.txt
yamanifest.egg-info/entry_points.txt
yamanifest.egg-info/not-zip-safe
yamanifest.egg-info/pbr.json
yamanifest.egg-info/requires.txt
yamanifest.egg-info/top_level.txt