Metadata-Version: 2.1
Name: yamanifest
Version: 0.3.8
Summary: General YAML manifest format
Home-page: UNKNOWN
Author: Aidan Heerdegen
Author-email: aidan.heerdegen@anu.edu.au
License: UNKNOWN
Platform: UNKNOWN
Classifier: Development Status :: 3 - Alpha
Classifier: Environment :: Console
Classifier: Intended Audience :: Science/Research
Classifier: License :: OSI Approved :: Apache Software License
Classifier: Operating System :: POSIX :: Linux
Classifier: Programming Language :: Python :: 2.6
Classifier: Programming Language :: Python :: 2.7
Classifier: Programming Language :: Python :: 3.5
Provides-Extra: dev
